{
    "case_id": "603A-10",
    "commit": "6bc02f8a600b35639bc9a4281695400e8a9a5606",
    "metrics": {
        "FPF": 0.0391566265060241,
        "TPF": 0.9522388059701492,
        "fraction_of_volume_covered": 1.0,
        "max_distortion": 1.5932288373510521,
        "median_distortion": 0.23635384535533935,
        "min_distortion": 0.0,
        "registration_shift": 32.76885855844953
    },
    "ran_on": 1515557737.908838,
    "repo_dirty": true,
    "result_id": "1515557737.908838_6bc02f8a600b35639bc9a4281695400e8a9a5606",
    "status": "fail",
    "suite_id": "full-algorithm"
}